Workbook

Sheet RESUMEN
A1: Modelo Financiero - Fondo Emprender (SENA)
A3: Rubro | B3: Valor (COP)
A4: Talento Humano | B4: 75000000
A5: Infraestructura Tecnológica | B5: 36000000
A6: Mercadeo y Ventas | B6: 10000000
A7: Legal y Activos | B7: 5000000
A8: GRAN TOTAL | B8: =SUM(B4:B7) -> 126000000
A10: Resumen: El proyecto destina el 60% de los recursos a la generación de empleo formal calificado y el 29% a infraestructura tecnológica para desarrollo y operación del software.

Sheet DETALLE NÓMINA
A1: Detalle Nómina (Talento Humano)
A3: Cargo | B3: Cantidad | C3: Meses | D3: Valor Mensual | E3: Total
A4: Desarrollador Junior (OPS) | B4: 1 | C4: 12 | D4: 2000000 | E4: =B4*C4*D4 -> 24000000
A5: Auxiliar Operativo | B5: 1 | C5: 6 | D5: 1500000 | E5: =B5*C5*D5 -> 9000000
A6: Director de Proyecto | B6: 1 | C6: 12 | D6: 3500000 | E6: =B6*C6*D6 -> 42000000
D8: TOTAL NÓMINA | E8: =SUM(E4:E6) -> 75000000

Sheet TECNOLOGÍA
A1: Infraestructura Tecnológica
A3: Concepto | B3: Cantidad | C3: Valor Unitario | D3: Total
A4: Servidor / Hosting (AWS, Azure) - 12 meses | B4: 1 | C4: 12000000 | D4: =B4*C4 -> 12000000
A5: Licencias Software (CRM, herramientas) - 12 meses | B5: 1 | C5: 18000000 | D5: =B5*C5 -> 18000000
A6: WhatsApp Business API | B6: 2 | C6: 3000000 | D6: =B6*C6 -> 6000000
C8: TOTAL TECNOLOGÍA | D8: =SUM(D4:D6) -> 36000000

Sheet MERCADEO Y VENTAS
A1: Mercadeo y Ventas
A3: Actividad | B3: Cantidad | C3: Costo Unitario | D3: Total
A4: Campañas digitales (Facebook, Google) - 6 meses | B4: 6 | C4: 1000000 | D4: =B4*C4 -> 6000000
A5: Diseño de Marca e identidad visual | B5: 1 | C5: 2000000 | D5: =B5*C5 -> 2000000
A6: Producción de Video Promocional y Tutoriales | B6: 4 | C6: 500000 | D6: =B6*C6 -> 2000000
C8: TOTAL MERCADEO | D8: =SUM(D4:D6) -> 10000000

Sheet LEGAL Y ACTIVOS
A1: Legal y Activos
A3: Concepto | B3: Cantidad | C3: Costo Unitario | D3: Total
A5: Constitución Empresa (Cámara de Comercio, RUT) | B5: 1 | C5: 1000000 | D5: =B5*C5 -> 1000000
A6: Computadores Portátiles de Alto Rendimiento (2 Unidades) | B6: 2 | C6: 2000000 | D6: =B6*C6 -> 4000000
C8: TOTAL LEGAL/ACTIVOS | D8: =SUM(D4:D6) -> 5000000

Sheet FLUJO DE CAJA
A1: Flujo de Caja (Año 1)
A3: Concepto | B3: Mes 1 | C3: Mes 2 | D3: Mes 3 | E3: Mes 4 | F3: Mes 5 | G3: Mes 6 | H3: Mes 7 | I3: Mes 8 | J3: Mes 9 | K3: Mes 10 | L3: Mes 11 | M3: Mes 12
A4: Ingresos | B4: 0 | C4: 0 | D4: 0 | E4: 0 | F4: 0 | G4: 0 | H4: 2000000 | I4: 2000000 | J4: 2000000 | K4: 2000000 | L4: 2000000 | M4: 2000000
A5: Egresos | B5: 10500000 | C5: 10500000 | D5: 10500000 | E5: 10500000 | F5: 10500000 | G5: 10500000 | H5: 10500000 | I5: 10500000 | J5: 10500000 | K5: 10500000 | L5: 10500000 | M5: 10500000
A6: Saldo | B6: =B4-B5 -> -10500000 | C6: =C4-C5 -> -10500000 | D6: =D4-D5 -> -10500000 | E6: =E4-E5 -> -10500000 | F6: =F4-F5 -> -10500000 | G6: =G4-G5 -> -10500000 | H6: =H4-H5 -> -8500000 | I6: =I4-I5 -> -8500000 | ... M6: =M4-M5 -> -8500000
A8: Nota: El déficit operativo se cubre con el Capital Semilla del Fondo Emprender.

Sheet PROYECCIÓN VENTAS
A1: Proyección de Ventas (3 Años)
A3: Año | B3: Sedes Vendidas | C3: Precio por Sede (anual) | D3: Total Ventas
A4: 1 | B4: 2 | C4: 12000000 | D4: =B4*C4 -> 24000000
A5: 2 | B5: 6 | C5: 12000000 | D5: =B5*C5 -> 72000000
A6: 3 | B6: 15 | C6: 12000000 | D6: =B6*C6 -> 180000000
C8: TOTAL 3 AÑOS | D8: =SUM(D4:D6) -> 276000000

Sheet INDICADORES
A1: Indicadores Clave
A3: Indicador | B3: Fórmula | C3: Valor | D3: Meta / Comentario
A4: Inversión Total (Capital Semilla) | B4: =RESUMEN!B8 -> 126000000 | C4: =RESUMEN!B8 -> 126000000 | D4: Debe ser 126,000,000 COP
A5: Total Nómina | B5: ='DETALLE NÓMINA'!E8 -> 75000000 | C5: ='DETALLE NÓMINA'!E8 -> 75000000 | D5: Cubre equipo base de operación
A6: Total Tecnología | B6: =TECNOLOGÍA!D8 -> 36000000 | C6: =TECNOLOGÍA!D8 -> 36000000 | D6: Infraestructura, licencias, equipos
A7: Total Mercadeo | B7: ='MERCADEO Y VENTAS'!D8 -> 10000000 | C7: ='MERCADEO Y VENTAS'!D8 -> 10000000 | D7: Adquisición y activación comercial
A8: Total Legal/Activos | B8: ='LEGAL Y ACTIVOS'!D8 -> 5000000 | C8: ='LEGAL Y ACTIVOS'!D8 -> 5000000 | D8: Formalización y activos mínimos
A10: CAC aproximado (Año 1) | B10: 2000000 | C10: 2000000 | D10: Mercadeo / clientes año 1
A11: Burn mensual (Meses 1-6) | B11: 10500000 | C11: 10500000 | D11: Egresos netos promedio primeros 6 meses
A12: Runway (meses) | B12: =C4/C11 -> 12 | C12: =C4/C11 -> 12 | D12: Tiempo estimado con capital semilla
A14: Nota: Indicadores calculados con supuestos del flujo de caja y proyección de ventas. Ajuste ingresos/egresos para recalcular automáticamente.
